jsongrep/VERSION
jsongrep/__init__.py
jsongrep/main.py
jsongrep/postinstall.sh
jsongrep/libs/__init__.py
jsongrep/libs/cli_colors.py
jsongrep/libs/first_run.py
jsongrep/libs/json_filter.py
jsongrep/libs/setuptools.py
json_grep-1.4.7.dist-info/METADATA
json_grep-1.4.7.dist-info/WHEEL
json_grep-1.4.7.dist-info/entry_points.txt
json_grep-1.4.7.dist-info/top_level.txt
json_grep-1.4.7.dist-info/RECORD
