Metadata-Version: 2.1
Name: json-grep
Version: 1.4.7
Summary: Filtering JSON dict keys from STDOUT
Home-page: https://gitlab.com/alda78/json-grep
Author: Ales Adamek
Author-email: alda78@seznam.cz
License: MIT
Classifier: Programming Language :: Python :: 3
Classifier: License :: OSI Approved :: MIT License
Classifier: Operating System :: OS Independent
Requires-Python: >=3.6
Requires-Dist: al78tools
Requires-Dist: argcomplete
